fastpluggy_plugin/__init__.py
fastpluggy_plugin/bootstrap.py
fastpluggy_plugin/auth_user/__init__.py
fastpluggy_plugin/auth_user/config.py
fastpluggy_plugin/auth_user/models.py
fastpluggy_plugin/auth_user/plugin.py
fastpluggy_plugin/auth_user/repository.py
fastpluggy_plugin/auth_user/templates/profile.html.j2
fastpluggy_plugin/crud_tools/__init__.py
fastpluggy_plugin/crud_tools/config.py
fastpluggy_plugin/crud_tools/crud_admin.py
fastpluggy_plugin/crud_tools/crud_admin_registry.py
fastpluggy_plugin/crud_tools/crud_link_helper.py
fastpluggy_plugin/crud_tools/menu_tools.py
fastpluggy_plugin/crud_tools/plugin.py
fastpluggy_plugin/crud_tools/schema.py
fastpluggy_plugin/crud_tools/template_tools.py
fastpluggy_plugin/crud_tools/static/css/header_filters.css
fastpluggy_plugin/crud_tools/static/js/dynamic-select.js
fastpluggy_plugin/crud_tools/templates/widgets/data/filter_macros.html.j2
fastpluggy_plugin/crud_tools/templates/widgets/data/filtered_table.html.j2
fastpluggy_plugin/debug_tools/__init__.py
fastpluggy_plugin/debug_tools/plugin.py
fastpluggy_plugin/debug_tools/requirements_tools.py
fastpluggy_plugin/redis_tools/__init__.py
fastpluggy_plugin/redis_tools/config.py
fastpluggy_plugin/redis_tools/plugin.py
fastpluggy_plugin/redis_tools/redis_connector.py
fastpluggy_plugin/redis_tools/router.py
fastpluggy_plugin/redis_tools/schema.py
fastpluggy_plugin/redis_tools/stats_card_tools.py
fastpluggy_plugin/redis_tools/templates/browser.html.j2
fastpluggy_plugin/scheduled_query/__init__.py
fastpluggy_plugin/scheduled_query/config.py
fastpluggy_plugin/scheduled_query/metrics.py
fastpluggy_plugin/scheduled_query/models.py
fastpluggy_plugin/scheduled_query/plugin.py
fastpluggy_plugin/scheduled_query/router.py
fastpluggy_plugin/scheduled_query/tasks.py
fastpluggy_plugin/scheduled_query/templates/scheduled_query_result_card.html.j2
fastpluggy_plugin/tasks_worker/__init__.py
fastpluggy_plugin/tasks_worker/config.py
fastpluggy_plugin/tasks_worker/log_handler.py
fastpluggy_plugin-0.0.42.dist-info/METADATA
fastpluggy_plugin-0.0.42.dist-info/WHEEL
fastpluggy_plugin-0.0.42.dist-info/entry_points.txt
fastpluggy_plugin-0.0.42.dist-info/top_level.txt
fastpluggy_plugin-0.0.42.dist-info/RECORD
