Metadata-Version: 2.4
Name: fastpluggy_plugin
Version: 0.0.42
Summary: Official plugin bundle for FastPluggy
Author-email: Your Name <you@example.com>
Requires-Python: >=3.10
Requires-Dist: jinja2
Requires-Dist: redis
Requires-Dist: croniter
Requires-Dist: psutil
Requires-Dist: loguru
Requires-Dist: prometheus_client
Requires-Dist: babel
Requires-Dist: passlib
Requires-Dist: python-jose
Requires-Dist: python-multipart
Requires-Dist: packaging
